{
  "objectInfo" : {
    "id" : "8YIhBYqPs0yiFS8XpPYRsb",
    "name" : "Admin_APIWorkletEnd",
    "type" : "DTEMPLATE",
    "metadata" : {
      "modelVersion" : {
        "major" : 0,
        "minor" : 0
      },
      "repoInfo" : {
        "repoHandle" : "01C1HR170000000000A2"
      },
      "contextAttributes" : [ {
        "name" : "id",
        "value" : "@1"
      } ],
      "additionalInfo" : {
        "description" : "",
        "contentType" : "JSON",
        "documentState" : "VALID"
      }
    }
  },
  "dataFileExtension" : "zip",
  "objectRefs" : [ ]
}